timer/__init__.py
timer/py.typed
timer/version.py
timer/constant/__init__.py
timer/constant/decimals.py
timer/constant/various.py
timer/controller/__init__.py
timer/decorator/__init__.py
timer/decorator/function.py
timer/error/__init__.py
timer/helper/__init__.py
timer/helper/decimals.py
timer/helper/output.py
timer/helper/time_fractions.py
timer/helper/thread/__init__.py
timer/helper/thread/list.py
timer/model/__init__.py
timer/model/elapsed_time_fractions.py
timer/model/thread_item.py
timer/model/time_fractions.py
timer/model/timer.py
timer/model/timer_base.py
timer/model/abc/mkdocstrings.py
timer_for_python-0.9.6.dist-info/licenses/LICENSE.md
timer_for_python-0.9.6.dist-info/METADATA
timer_for_python-0.9.6.dist-info/WHEEL
timer_for_python-0.9.6.dist-info/top_level.txt
timer_for_python-0.9.6.dist-info/RECORD
