Metadata-Version: 2.4
Name: timer-for-python
Version: 0.9.6
Summary: Lightweight package that makes it easy to measure how much time it takes to run Python programs and gauge performance of multiple, smaller bits of code
Home-page: https://jakob-bagterp.github.io/timer-for-python/
Download-URL: https://pypi.org/project/timer-for-python/
Author: Jakob Bagterp
Author-email: jakob_bagterp@hotmail.com
Maintainer: Jakob Bagterp
Maintainer-email: jakob_bagterp@hotmail.com
License: MIT License
Project-URL: Bug Tracker, https://github.com/jakob-bagterp/timer-for-python/issues
Project-URL: Documentation, https://jakob-bagterp.github.io/timer-for-python/
Project-URL: API Reference, https://jakob-bagterp.github.io/timer-for-python/reference/
Project-URL: Source Code, https://github.com/jakob-bagterp/timer-for-python
Project-URL: Release Notes, https://github.com/jakob-bagterp/timer-for-python/releases
Keywords: python,timer
Classifier: Programming Language :: Python :: 3
Classifier: Programming Language :: Python :: 3.10
Classifier: Programming Language :: Python :: 3.11
Classifier: Programming Language :: Python :: 3.12
Classifier: Programming Language :: Python :: 3.13
Classifier: Programming Language :: Python :: 3.14
Classifier: License :: OSI Approved :: MIT License
Classifier: Operating System :: OS Independent
Requires-Python: >=3.10
License-File: LICENSE.md
Requires-Dist: colorist==1.8.8
Provides-Extra: testing
Requires-Dist: coverage==7.11.0; extra == "testing"
Requires-Dist: flake8==7.3.0; extra == "testing"
Requires-Dist: mypy==1.19.0; extra == "testing"
Requires-Dist: pytest==9.0.1; extra == "testing"
Requires-Dist: pytest-cov==7.0.0; extra == "testing"
Requires-Dist: tox==4.32.0; extra == "testing"
Dynamic: download-url
Dynamic: license-file
